jobwrapper/LPPic.py
jobwrapper/__init__.py
jobwrapper/inputclass.py
jobwrapper/inspect_exec.py
jobwrapper/job_watcher.py
jobwrapper/mail.py
jobwrapper/preporc.py
jobwrapper/readTemp.py
jobwrapper/run_sbatch.py
jobwrapper/slurm_wrapper.py
jobwrapper-0.1.1.dist-info/METADATA
jobwrapper-0.1.1.dist-info/RECORD
jobwrapper-0.1.1.dist-info/WHEEL
jobwrapper-0.1.1.dist-info/top_level.txt
