Metadata-Version: 2.1
Name: jobwrapper
Version: 0.1.1
Summary: Wrappe slurm utilies for python
Home-page: https://github.com/antoinelpp/jobWrapper
Author: Antoine Tavant
Author-email: antoinetavant@hotmail.fr
License: UNKNOWN
Platform: UNKNOWN
Requires-Dist: scipy
Requires-Dist: numpy
Requires-Dist: matplotlib
